{
  "fileName": "IMessageSerializer.cs",
  "filePath": "src/Nethermind/Nethermind.Network/IMessageSerializer.cs",
  "url": "https://github.com/nethermindeth/nethermind/Nethermind.Network/IMessageSerializer.cs",
  "summary": "The code above defines an interface called `IMessageSerializer` that is used for serializing and deserializing messages in the Nethermind network. The interface is generic, meaning it can be used with any type of message that inherits from the `MessageBase` class. \n\nThe `Serialize` method takes a message of type `T` and returns a byte array that represents the serialized message. This method is used to convert a message object into a format that can be transmitted over the network. \n\nThe `Deserialize` method takes a byte array that represents a serialized message and returns an object of type `T`. This method is used to convert a received message into an object that can be processed by the application. \n\nThis interface is likely used by other classes in the Nethermind network that need to send or receive messages. For example, a class that handles incoming network traffic may use the `Deserialize` method to convert received messages into objects that can be processed by the application. Similarly, a class that sends messages over the network may use the `Serialize` method to convert message objects into a format that can be transmitted. \n\nHere is an example of how this interface might be used in a class that sends messages over the network:\n\n```\npublic class MessageSender\n{\n    private readonly IMessageSerializer<MyMessage> _serializer;\n    private readonly INetworkConnection _connection;\n\n    public MessageSender(IMessageSerializer<MyMessage> serializer, INetworkConnection connection)\n    {\n        _serializer = serializer;\n        _connection = connection;\n    }\n\n    public void SendMessage(MyMessage message)\n    {\n        byte[] serializedMessage = _serializer.Serialize(message);\n        _connection.Send(serializedMessage);\n    }\n}\n```\n\nIn this example, the `MessageSender` class takes an instance of `IMessageSerializer<MyMessage>` and an instance of `INetworkConnection` in its constructor. The `SendMessage` method takes a `MyMessage` object, serializes it using the serializer, and sends the resulting byte array over the network using the connection object.",
  "questions": "1. What is the purpose of this code?\n   This code defines an interface called `IMessageSerializer` that specifies methods for serializing and deserializing messages of type `T`, which must be a subclass of `MessageBase`.\n\n2. What is the significance of the `namespace` declaration?\n   The `namespace` declaration specifies that this code belongs to the `Nethermind.Network` namespace, which is a way of organizing related code and avoiding naming conflicts with other code.\n\n3. What is the meaning of the `where` keyword in the interface definition?\n   The `where` keyword is used to specify a constraint on the generic type parameter `T`. In this case, it specifies that `T` must be a subclass of `MessageBase`. This ensures that any implementation of `IMessageSerializer` will only work with messages that inherit from `MessageBase`.",
  "checksum": "da71eceec29be0f3741d9db43e022da5"
}