{
  "fileName": "SearchResult.cs",
  "filePath": "src/Nethermind/Nethermind.JsonRpc/Modules/SearchResult.cs",
  "url": "https://github.com/NethermindEth/nethermind/src/Nethermind/Nethermind.JsonRpc/Modules/SearchResult.cs",
  "summary": "This code defines a struct called `SearchResult` that is used in the Nethermind project's JSON-RPC modules. The struct is generic and takes a type parameter `T` that must be a reference type (i.e. a class). \n\nThe `SearchResult` struct has two constructors. The first constructor takes two parameters: an error message and an error code. It sets the `Object` property to `null`, sets the `Error` property to the provided error message, and sets the `ErrorCode` property to the provided error code. This constructor is used to create a `SearchResult` object when an error occurs during a search operation.\n\nThe second constructor takes a single parameter of type `T` and sets the `Object` property to the provided object. It sets the `Error` property to `null` and the `ErrorCode` property to `0`. This constructor is used to create a `SearchResult` object when a search operation is successful and returns a result.\n\nThe `SearchResult` struct has three properties: `Object`, `Error`, and `ErrorCode`. The `Object` property is of type `T?`, which means it can be `null` or of type `T`. This property holds the result of a successful search operation. The `Error` property is of type `string?`, which means it can be `null` or of type `string`. This property holds the error message when an error occurs during a search operation. The `ErrorCode` property is of type `int` and holds the error code when an error occurs during a search operation.\n\nThe `SearchResult` struct also has a read-only property called `IsError` that returns a boolean value indicating whether an error occurred during a search operation. It does this by checking whether the `ErrorCode` property is not equal to `0`.\n\nOverall, this code provides a simple and reusable way to represent the results of search operations in the Nethermind project's JSON-RPC modules. It allows for easy handling of both successful and failed search operations by providing a consistent interface for accessing the results and any associated error messages or codes. An example usage of this struct might be in a method that searches for a block by its hash and returns a `SearchResult<Block>` object.",
  "questions": "1. What is the purpose of the `SearchResult` struct?\n- The `SearchResult` struct is used to represent the result of a search operation and can contain either an object of type `T` or an error message and code.\n\n2. What is the significance of the `where T : class` constraint in the `SearchResult` struct definition?\n- The `where T : class` constraint ensures that the type parameter `T` must be a reference type, which means it cannot be a value type like `int` or `bool`.\n\n3. What is the purpose of the `IsError` property in the `SearchResult` struct?\n- The `IsError` property returns a boolean value indicating whether the `SearchResult` instance represents an error or not, based on the value of the `ErrorCode` property."
}