{
  "fileName": "ReceiptMessageDecoder.cs",
  "filePath": "src/Nethermind/Nethermind.Serialization.Rlp/ReceiptMessageDecoder.cs",
  "url": "https://github.com/nethermindeth/nethermind/Nethermind.Serialization.Rlp/ReceiptMessageDecoder.cs",
  "summary": "The `ReceiptMessageDecoder` class is responsible for decoding and encoding Ethereum transaction receipts in RLP (Recursive Length Prefix) format. RLP is a serialization format used in Ethereum to encode data structures like transactions, blocks, and receipts. \n\nThe `ReceiptMessageDecoder` class implements the `IRlpStreamDecoder<TxReceipt>` interface, which defines a single method `Decode` that takes an RLP stream and returns a `TxReceipt` object. The `Decode` method first checks if the next item in the stream is null, in which case it returns null. Otherwise, it reads the RLP-encoded fields of the receipt and constructs a `TxReceipt` object. The `TxReceipt` object contains fields like `GasUsedTotal`, `StatusCode`, `Bloom`, and `Logs`, which are populated by decoding the corresponding fields in the RLP stream.\n\nThe `ReceiptMessageDecoder` class also implements two methods `GetLength` and `Encode` that are used to encode a `TxReceipt` object into an RLP stream. The `GetLength` method calculates the length of the RLP-encoded `TxReceipt` object, while the `Encode` method writes the RLP-encoded fields of the `TxReceipt` object to an RLP stream.\n\nThe `ReceiptMessageDecoder` class is used in the larger Nethermind project to decode and encode Ethereum transaction receipts in RLP format. Transaction receipts are generated by Ethereum nodes as a result of executing a transaction on the blockchain. The receipt contains information about the transaction, such as the amount of gas used, the status code, and the logs generated by the transaction. The `ReceiptMessageDecoder` class is used to serialize and deserialize these receipts between the Ethereum nodes in the network. \n\nHere is an example of how the `ReceiptMessageDecoder` class can be used to decode an RLP-encoded transaction receipt:\n\n```\nbyte[] rlpEncodedReceipt = ... // RLP-encoded transaction receipt\nRlpStream rlpStream = new RlpStream(rlpEncodedReceipt);\nReceiptMessageDecoder decoder = new ReceiptMessageDecoder();\nTxReceipt receipt = decoder.Decode(rlpStream);\n```\n\nIn this example, we first create an RLP stream from the RLP-encoded transaction receipt. We then create an instance of the `ReceiptMessageDecoder` class and use it to decode the RLP stream into a `TxReceipt` object. The resulting `TxReceipt` object contains the decoded fields of the transaction receipt.",
  "questions": "1. What is the purpose of this code file?\n- This code file contains a class called `ReceiptMessageDecoder` that implements the `IRlpStreamDecoder` interface for decoding transaction receipts in RLP format.\n\n2. What is the significance of the `RlpBehaviors` parameter in the `Decode`, `GetLength`, and `Encode` methods?\n- The `RlpBehaviors` parameter is used to specify additional behaviors for RLP encoding and decoding, such as skipping typed wrapping or using EIP-658 receipts.\n\n3. What is the purpose of the `GetContentLength` and `GetLogsLength` methods?\n- The `GetContentLength` method calculates the total length of the RLP-encoded content of a transaction receipt, while the `GetLogsLength` method calculates the length of the RLP-encoded logs of the receipt. These methods are used in the `GetLength` and `Encode` methods to determine the length of the RLP-encoded receipt.",
  "checksum": "924a2a034229ebd4880e37e443931e48"
}