{
  "$schema": "https://raw.githubusercontent.com/NethermindEth/core-scripts/refs/heads/main/schemas/config.json",
  "Init": {
    "ChainSpecPath": "chainspec/race-sepolia.json.zst",
    "GenesisHash": "0x994d67464c3368b8eb6f9770087399486b25d721a1868b95bb37de327b49ab89",
    "BaseDbPath": "nethermind_db/race-sepolia",
    "LogFileName": "race-sepolia.log"
  },
  "TxPool": {
    "BlobsSupport": "Disabled"
  },
  "Sync": {
    "FastSync": true,
    "SnapSync": true,
    "FastSyncCatchUpHeightDelta": "10000000000"
  },
  "Discovery": {
    "DiscoveryVersion": "V5"
  },
  "JsonRpc": {
    "Enabled": true,
    "Port": 8545,
    "EnginePort": 8551
  },
  "Pruning": {
    "PruningBoundary": 192
  },
  "Blocks": {
    "SecondsPerSlot": 2
  },
  "Merge": {
    "Enabled": true
  },
  "Optimism": {
    "SequencerUrl": "https://racetestnet.io"
  }
}