{
  "fileName": "NoBlockRewards.cs",
  "filePath": "src/Nethermind/Nethermind.Consensus/Rewards/NoBlockRewards.cs",
  "url": "https://github.com/NethermindEth/nethermind/src/Nethermind/Nethermind.Consensus/Rewards/NoBlockRewards.cs",
  "summary": "The code above defines a class called `NoBlockRewards` that implements two interfaces: `IRewardCalculator` and `IRewardCalculatorSource`. This class is part of the Nethermind project and is responsible for calculating block rewards for a given block. \n\nThe `IRewardCalculator` interface defines a method called `CalculateRewards` that takes a `Block` object as input and returns an array of `BlockReward` objects. In this implementation, the `CalculateRewards` method always returns an empty array, indicating that there are no rewards for the given block. \n\nThe `IRewardCalculatorSource` interface defines a method called `Get` that takes an `ITransactionProcessor` object as input and returns an instance of `IRewardCalculator`. In this implementation, the `Get` method always returns an instance of `NoBlockRewards`, indicating that there are no rewards to be calculated. \n\nThe purpose of this class is to provide a default implementation of the `IRewardCalculator` interface that can be used when there are no rewards to be calculated. This can be useful in situations where a consensus algorithm does not provide any rewards for mining a block, or when a block is being created for testing purposes and rewards are not necessary. \n\nHere is an example of how this class can be used:\n\n```\nBlock block = new Block();\nIRewardCalculatorSource rewardCalculatorSource = new NoBlockRewards();\nIRewardCalculator rewardCalculator = rewardCalculatorSource.Get(null);\nBlockReward[] rewards = rewardCalculator.CalculateRewards(block);\n```\n\nIn this example, a new `Block` object is created and a new instance of `NoBlockRewards` is obtained from the `IRewardCalculatorSource` interface. The `Get` method is called with a `null` argument because the `ITransactionProcessor` object is not needed in this case. Finally, the `CalculateRewards` method is called with the `Block` object as input, and an empty array is returned.",
  "questions": "1. What is the purpose of this code file?\n   - This code file contains a class called `NoBlockRewards` which implements two interfaces `IRewardCalculator` and `IRewardCalculatorSource`. It seems to be related to calculating rewards for a block in some consensus algorithm.\n\n2. What is the significance of the `Instance` property?\n   - The `Instance` property is a static property that returns a singleton instance of the `NoBlockRewards` class. This ensures that only one instance of the class is created and used throughout the application.\n\n3. What is the purpose of the `CalculateRewards` method?\n   - The `CalculateRewards` method takes a `Block` object as input and returns an array of `BlockReward` objects. It seems to be responsible for calculating the rewards for a given block, although in this implementation it always returns an empty array."
}