{
  "fileName": "LevelVisitOutcome.cs",
  "filePath": "src/Nethermind/Nethermind.Blockchain/Visitors/LevelVisitOutcome.cs",
  "url": "https://github.com/nethermindeth/nethermind/Nethermind.Blockchain/Visitors/LevelVisitOutcome.cs",
  "summary": "This code defines an enumeration called `LevelVisitOutcome` within the `Nethermind.Blockchain.Visitors` namespace. The `LevelVisitOutcome` enumeration is marked with the `[Flags]` attribute, which allows its values to be combined using bitwise OR operations.\n\nThe `LevelVisitOutcome` enumeration has four possible values: `None`, `DeleteLevel`, `StopVisiting`, and `All`. The `None` value has a default integer value of 0, while `DeleteLevel` has a value of 1, `StopVisiting` has a value of 2, and `All` has a value of 3.\n\nThis enumeration is likely used in other parts of the `Nethermind` project to represent the outcome of a visit to a particular level of a data structure or hierarchy. For example, a visitor pattern may be used to traverse a blockchain data structure, and the `LevelVisitOutcome` enumeration could be used to indicate whether the visitor should stop visiting or delete a particular level of the blockchain.\n\nHere is an example of how the `LevelVisitOutcome` enumeration could be used in code:\n\n```\npublic LevelVisitOutcome VisitLevel(Block block)\n{\n    // Visit the block and determine the outcome\n    LevelVisitOutcome outcome = LevelVisitOutcome.None;\n    if (block.IsInvalid)\n    {\n        outcome |= LevelVisitOutcome.DeleteLevel;\n    }\n    if (block.IsLastBlock)\n    {\n        outcome |= LevelVisitOutcome.StopVisiting;\n    }\n    return outcome;\n}\n```\n\nIn this example, the `VisitLevel` method visits a `Block` object and determines the outcome of the visit based on the block's properties. If the block is invalid, the `DeleteLevel` flag is set in the `outcome` variable using bitwise OR. If the block is the last block in the chain, the `StopVisiting` flag is set. The `outcome` variable is then returned to indicate the outcome of the visit.",
  "questions": "1. What is the purpose of the `LevelVisitOutcome` enum?\n   - The `LevelVisitOutcome` enum is used to represent the possible outcomes of visiting a level in the blockchain.\n\n2. What do the different values of the `LevelVisitOutcome` enum represent?\n   - The `None` value represents no outcome, `DeleteLevel` represents the deletion of the current level, `StopVisiting` represents the stopping of further level visits, and `All` represents both the deletion of the current level and the stopping of further level visits.\n\n3. What is the significance of the `[Flags]` attribute applied to the `LevelVisitOutcome` enum?\n   - The `[Flags]` attribute indicates that the values of the `LevelVisitOutcome` enum can be combined using bitwise OR operations.",
  "checksum": "0e7693eec9a041d2a33dc85f4cbab89d"
}