{
  "fileName": "UnixTime.cs",
  "filePath": "src/Nethermind/Nethermind.Core/UnixTime.cs",
  "url": "https://github.com/NethermindEth/nethermind/src/Nethermind/Nethermind.Core/UnixTime.cs",
  "summary": "The code defines a struct called `UnixTime` that represents a Unix timestamp. Unix timestamps are a way of representing time as the number of seconds or milliseconds that have elapsed since January 1, 1970, at 00:00:00 UTC. The `UnixTime` struct provides a way to create Unix timestamps from `DateTime` or `DateTimeOffset` objects, and to retrieve the number of seconds or milliseconds that have elapsed since the Unix epoch.\n\nThe `UnixTime` struct has three public properties: `Seconds`, `Milliseconds`, and `SecondsLong`. The `Seconds` and `Milliseconds` properties return the number of seconds and milliseconds that have elapsed since the Unix epoch, respectively, as `ulong` values. The `SecondsLong` property returns the number of seconds that have elapsed since the Unix epoch as a `long` value.\n\nThe `UnixTime` struct has two constructors: one that takes a `DateTime` object and one that takes a `DateTimeOffset` object. The `FromSeconds` method is a static factory method that takes a `double` value representing the number of seconds that have elapsed since the Unix epoch and returns a new `UnixTime` object.\n\nThe purpose of this code is to provide a convenient way to work with Unix timestamps in the Nethermind project. Unix timestamps are commonly used in blockchain applications to represent block timestamps, transaction timestamps, and other time-related data. The `UnixTime` struct can be used throughout the Nethermind codebase to create, manipulate, and compare Unix timestamps. For example, the following code creates a `UnixTime` object representing the current time:\n\n```csharp\nUnixTime now = new UnixTime(DateTimeOffset.UtcNow);\n```\n\nOverall, the `UnixTime` struct provides a simple and efficient way to work with Unix timestamps in the Nethermind project.",
  "questions": "1. What is the purpose of the UnixTime struct?\n    \n    The UnixTime struct is used to ensure that the same timestamp is used when calculating both seconds and milliseconds.\n\n2. How can a UnixTime object be created from seconds?\n    \n    A UnixTime object can be created from seconds using the static FromSeconds method, which takes a double parameter representing the number of seconds since Unix epoch.\n\n3. What is the difference between Seconds and Milliseconds properties?\n    \n    The Seconds property returns the number of seconds since Unix epoch as an unsigned long, while the Milliseconds property returns the number of milliseconds since Unix epoch as an unsigned long."
}