{
  "fileName": "ProtocolEventArgs.cs",
  "filePath": "src/Nethermind/Nethermind.Network/P2P/EventArg/ProtocolEventArgs.cs",
  "url": "https://github.com/NethermindEth/nethermind/src/Nethermind/Nethermind.Network/P2P/EventArg/ProtocolEventArgs.cs",
  "summary": "The code above defines a class called `ProtocolEventArgs` that inherits from the `System.EventArgs` class. This class is used to represent the event arguments for a protocol event in the Nethermind project. \n\nThe `ProtocolEventArgs` class has two properties: `Version` and `ProtocolCode`. The `Version` property is an integer that represents the version of the protocol, while the `ProtocolCode` property is a string that represents the code of the protocol. These properties are set in the constructor of the class, which takes in a `protocolCode` string and a `version` integer.\n\nThis class is likely used in the larger Nethermind project to provide information about protocol events that occur during the execution of the project. For example, when a new protocol is added or updated, an event may be raised that includes a `ProtocolEventArgs` object with information about the new or updated protocol. Other parts of the project can then use this information to update their own state or behavior accordingly.\n\nHere is an example of how this class might be used in the Nethermind project:\n\n```\npublic class ProtocolManager\n{\n    public event EventHandler<ProtocolEventArgs> ProtocolAdded;\n\n    public void AddProtocol(string protocolCode, int version)\n    {\n        // Add the protocol to the manager...\n\n        // Raise the ProtocolAdded event with the new protocol information\n        ProtocolAdded?.Invoke(this, new ProtocolEventArgs(protocolCode, version));\n    }\n}\n```\n\nIn this example, the `ProtocolManager` class has an `event` called `ProtocolAdded` that is raised whenever a new protocol is added to the manager. When the `AddProtocol` method is called, it adds the new protocol to the manager and then raises the `ProtocolAdded` event with a new `ProtocolEventArgs` object that contains information about the new protocol. Other parts of the project can then subscribe to this event and receive the `ProtocolEventArgs` object to update their own state or behavior accordingly.",
  "questions": "1. **What is the purpose of this code?** \nThis code defines a class called `ProtocolEventArgs` within the `Nethermind.Network.P2P.EventArg` namespace. The class has two properties, `Version` and `ProtocolCode`, and a constructor that initializes these properties.\n\n2. **What is the significance of the `SPDX-License-Identifier` comment?** \nThe `SPDX-License-Identifier` comment is used to specify the license under which the code is released. In this case, the code is released under the LGPL-3.0-only license.\n\n3. **What is the expected usage of the `ProtocolEventArgs` class?** \nThe `ProtocolEventArgs` class is likely intended to be used as an argument in an event that is raised when a protocol is invoked or updated. The `Version` property could be used to track changes to the protocol, while the `ProtocolCode` property could be used to identify the specific protocol being invoked or updated."
}