{
  "fileName": "ISocketsClient.cs",
  "filePath": "src/Nethermind/Nethermind.Sockets/ISocketsClient.cs",
  "url": "https://github.com/nethermindeth/nethermind/Nethermind.Sockets/ISocketsClient.cs",
  "summary": "The code provided is an interface definition for a higher-level socket communication logic that is not linked to any specific socket implementation like WebSockets or network sockets. This interface is called `ISocketsClient` and is located in the `Nethermind.Sockets` namespace.\n\nThe `ISocketsClient` interface defines two properties and two methods. The `Id` property is a string that represents the unique identifier of the client. The `ClientName` property is also a string that represents the name of the client. The `ReceiveAsync()` method is an asynchronous method that receives a message from the socket. The `SendAsync()` method is also an asynchronous method that sends a message to the socket.\n\nThis interface is designed to be implemented by a class that provides the lower-level communication logic, which is defined by the `ISocketHandler` interface. The `ISocketHandler` interface is not defined in this code snippet, but it is referenced in the summary of the `ISocketsClient` interface.\n\nOverall, this code provides a high-level abstraction for socket communication that can be used in a larger project. By defining a common interface for socket communication, the project can use different socket implementations without having to change the higher-level logic. For example, if the project needs to switch from WebSockets to network sockets, it can simply implement the `ISocketHandler` interface for network sockets and use the same `ISocketsClient` interface for the higher-level logic. \n\nHere is an example of how this interface could be implemented:\n\n```csharp\npublic class MySocketClient : ISocketsClient\n{\n    private readonly ISocketHandler _socketHandler;\n\n    public MySocketClient(ISocketHandler socketHandler, string id, string clientName)\n    {\n        _socketHandler = socketHandler;\n        Id = id;\n        ClientName = clientName;\n    }\n\n    public string Id { get; }\n    public string ClientName { get; }\n\n    public async Task ReceiveAsync()\n    {\n        // Implement receive logic using _socketHandler\n        await _socketHandler.ReceiveAsync();\n    }\n\n    public async Task SendAsync(SocketsMessage message)\n    {\n        // Implement send logic using _socketHandler\n        await _socketHandler.SendAsync(message);\n    }\n\n    public void Dispose()\n    {\n        // Implement dispose logic\n        _socketHandler.Dispose();\n    }\n}\n```",
  "questions": "1. What is the purpose of the `ISocketsClient` interface?\n   - The `ISocketsClient` interface defines the logic behind a socket communication that is not linked to any specific socket implementation, and provides methods for receiving and sending messages.\n\n2. What is the relationship between `ISocketsClient` and `ISocketHandler`?\n   - `ISocketsClient` is an interface that defines the higher level operations of a socket communication, while `ISocketHandler` is an interface that provides the lower level communication implementation. `ISocketsClient` relies on `ISocketHandler` to handle the actual socket communication.\n\n3. What is the significance of the `SPDX-License-Identifier` comment at the top of the file?\n   - The `SPDX-License-Identifier` comment specifies the license under which the code is released. In this case, the code is released under the LGPL-3.0-only license.",
  "checksum": "47e5eab712367252d8abbc02f97b2eab"
}