{
  "fileName": "IWorldState.cs",
  "filePath": "src/Nethermind/Nethermind.State/IWorldState.cs",
  "url": "https://github.com/NethermindEth/nethermind/src/Nethermind/Nethermind.State/IWorldState.cs",
  "summary": "The code above defines an interface called `IWorldState` that represents a state that can be anchored at a specific state root, snapshot, committed, or reverted. This interface is part of the Nethermind project and is used for state management.\n\nThe `IWorldState` interface inherits from the `IJournal` interface, which is a generic interface that defines methods for taking snapshots and reverting to previous states. The `IWorldState` interface adds two properties: `StorageProvider` and `StateProvider`, which are used for accessing the storage and state data associated with the world state.\n\nThe `TakeSnapshot` method is used to create a snapshot of the current state of the world. This method takes a boolean parameter called `newTransactionStart`, which indicates whether a new transaction should be started before taking the snapshot. If `newTransactionStart` is set to `true`, a new transaction will be started before the snapshot is taken. If it is set to `false`, the snapshot will be taken within the current transaction.\n\nThe `IJournal<Snapshot>.TakeSnapshot()` method is an explicit implementation of the `TakeSnapshot` method from the `IJournal` interface. This method simply calls the `TakeSnapshot` method defined in the `IWorldState` interface.\n\nOverall, the `IWorldState` interface is an important part of the Nethermind project's state management system. It provides a way to anchor the state of the world at specific points in time and to access the storage and state data associated with that state. Developers working on the Nethermind project can use this interface to manage the state of the system and to ensure that it remains consistent and reliable.",
  "questions": "1. What is the purpose of the `IWorldState` interface?\n   - The `IWorldState` interface represents state that can be anchored at specific state root, snapshot, committed, or reverted, and provides access to storage and state providers as well as a method to take a snapshot.\n2. What is the `IJournal` interface that `IWorldState` inherits from?\n   - The `IJournal` interface is a generic interface that defines a method to take a snapshot, and `IWorldState` inherits from it with the `Snapshot` type parameter.\n3. What is the significance of the comment in the `summary` tag of the `IWorldState` interface?\n   - The comment suggests that the current format of the `IWorldState` interface is not optimal and is being improved upon for better state management in the future."
}