{
  "fileName": "NullReceiptStorage.cs",
  "filePath": "src/Nethermind/Nethermind.Blockchain/Receipts/NullReceiptStorage.cs",
  "url": "https://github.com/NethermindEth/nethermind/src/Nethermind/Nethermind.Blockchain/Receipts/NullReceiptStorage.cs",
  "summary": "The code provided is a C# class called `NullReceiptStorage` that implements the `IReceiptStorage` interface. This class is part of the Nethermind project and is used to store transaction receipts for Ethereum blocks. \n\nThe purpose of this class is to provide a null implementation of the `IReceiptStorage` interface. This means that it does not actually store any receipts, but instead provides empty or null values for all of the methods that would normally interact with a storage system. \n\nThe `NullReceiptStorage` class is useful in situations where a developer wants to test or run code that requires an implementation of the `IReceiptStorage` interface, but does not want to actually store any receipts. By using this class, the developer can avoid the overhead of setting up a real storage system and instead use the null implementation provided by this class. \n\nThe class has several methods that return empty or null values. For example, the `FindBlockHash` method always returns null, indicating that the block hash cannot be found. The `Get` methods return an empty array of `TxReceipt` objects, indicating that there are no receipts for the given block or block hash. The `Insert` method does nothing, indicating that receipts are not actually being stored. \n\nThe `NullReceiptStorage` class also has several properties that are used to track the state of the storage system. For example, the `LowestInsertedReceiptBlockNumber` property always returns 0, indicating that no receipts have been inserted. The `MigratedBlockNumber` property is set to 0 by default, indicating that no blocks have been migrated. \n\nOverall, the `NullReceiptStorage` class is a useful tool for developers working on the Nethermind project who need to test or run code that requires an implementation of the `IReceiptStorage` interface, but do not want to actually store any receipts. By providing a null implementation of the interface, this class allows developers to avoid the overhead of setting up a real storage system and focus on testing and developing their code.",
  "questions": "1. What is the purpose of the `NullReceiptStorage` class?\n- The `NullReceiptStorage` class is an implementation of the `IReceiptStorage` interface and provides methods for inserting and retrieving transaction receipts for a block, but it does not actually store any data.\n\n2. What is the significance of the `Keccak` type used in this code?\n- The `Keccak` type is used to represent a hash value, and is used in this code to identify blocks and to find block hashes.\n\n3. What is the purpose of the `ReceiptsInserted` event?\n- The `ReceiptsInserted` event is not actually used in this implementation of `IReceiptStorage`, as the `add` and `remove` methods are empty. It is likely included for compatibility with other implementations of the interface."
}