{
  "fileName": "IBetterPeerStrategy.cs",
  "filePath": "src/Nethermind/Nethermind.Synchronization/IBetterPeerStrategy.cs",
  "url": "https://github.com/NethermindEth/nethermind/src/Nethermind/Nethermind.Synchronization/IBetterPeerStrategy.cs",
  "summary": "The code above defines an interface called `IBetterPeerStrategy` that provides an abstraction for checking if peers are available for syncing. This interface is part of the Nethermind project and is used to implement a better strategy for selecting peers to synchronize with.\n\nThe `IBetterPeerStrategy` interface has four methods: `Compare`, `IsBetterThanLocalChain`, `IsDesiredPeer`, and `IsLowerThanTerminalTotalDifficulty`. \n\nThe `Compare` method takes two tuples of `UInt256` and `long` values and returns an integer that represents the comparison between the two tuples. This method is used to compare the total difficulty and block number of two peers.\n\nThe `IsBetterThanLocalChain` method takes two tuples of `UInt256` and `long` values and returns a boolean that indicates whether the first tuple (representing a peer) is better than the second tuple (representing the local chain). This method is used to determine whether a peer should be selected for synchronization.\n\nThe `IsDesiredPeer` method takes two tuples of `UInt256` and `long` values and returns a boolean that indicates whether the first tuple (representing a peer) is a desired peer to synchronize with. This method is used to filter out unwanted peers.\n\nThe `IsLowerThanTerminalTotalDifficulty` method takes a `UInt256` value and returns a boolean that indicates whether the total difficulty of a peer is lower than the terminal total difficulty. This method is used to filter out peers that have a lower total difficulty than the terminal total difficulty.\n\nOverall, this interface provides a way to implement a better strategy for selecting peers to synchronize with in the Nethermind project. By defining these methods, the interface allows for more advanced filtering and selection of peers based on their total difficulty and block number.",
  "questions": "1. What is the purpose of this code?\n   - This code defines an interface called `IBetterPeerStrategy` which provides methods for checking if peers are available for syncing.\n\n2. What is the meaning of the `in` keyword used in the method signatures?\n   - The `in` keyword is used to pass parameters by reference without allowing them to be modified within the method.\n\n3. What is the significance of the `IsLowerThanTerminalTotalDifficulty` method?\n   - This method returns a boolean value indicating whether the given `totalDifficulty` is lower than the terminal total difficulty. The implementation always returns `true`, but it can be overridden in a derived class."
}