{
  "fileName": "IDiscoveryMsgListener.cs",
  "filePath": "src/Nethermind/Nethermind.Network.Discovery/IDiscoveryMsgListener.cs",
  "url": "https://github.com/NethermindEth/nethermind/src/Nethermind/Nethermind.Network.Discovery/IDiscoveryMsgListener.cs",
  "summary": "This code defines an interface called `IDiscoveryMsgListener` that is used in the Nethermind project for network discovery. The purpose of this interface is to provide a way for other parts of the project to listen for incoming messages related to network discovery.\n\nThe interface has a single method called `OnIncomingMsg` that takes a `DiscoveryMsg` object as a parameter. This method is called whenever a new discovery message is received by the network discovery system. The `DiscoveryMsg` object contains information about the message, such as the sender's IP address and port number.\n\nOther parts of the Nethermind project can implement this interface to receive incoming discovery messages. For example, a node that is participating in the network can implement this interface to receive messages from other nodes. Here is an example implementation of the `IDiscoveryMsgListener` interface:\n\n```\npublic class MyDiscoveryMsgListener : IDiscoveryMsgListener\n{\n    public void OnIncomingMsg(DiscoveryMsg msg)\n    {\n        // Handle the incoming message here\n    }\n}\n```\n\nIn this example, the `MyDiscoveryMsgListener` class implements the `OnIncomingMsg` method to handle incoming discovery messages. The implementation of this method will depend on the specific requirements of the project.\n\nOverall, this code provides a way for different parts of the Nethermind project to communicate with each other using discovery messages. By implementing the `IDiscoveryMsgListener` interface, nodes in the network can receive and process incoming messages, which is an important part of maintaining a healthy and functional network.",
  "questions": "1. What is the purpose of the `IDiscoveryMsgListener` interface?\n   - The `IDiscoveryMsgListener` interface is used to define a contract for classes that want to listen for incoming `DiscoveryMsg` messages in the `Nethermind` network discovery module.\n\n2. What is the `DiscoveryMsg` class and where is it defined?\n   - The `DiscoveryMsg` class is referenced in the `OnIncomingMsg` method signature and is likely defined in the `Nethermind.Network.Discovery.Messages` namespace. Further investigation of that namespace may reveal more information about the `DiscoveryMsg` class.\n\n3. What is the significance of the SPDX license identifier at the top of the file?\n   - The SPDX license identifier is used to indicate the license under which the code is released. In this case, the code is released under the LGPL-3.0-only license."
}