{
  "fileName": "PointEvaluationPrecompile.cs",
  "filePath": "src/Nethermind/Nethermind.Evm/Precompiles/PointEvaluationPrecompile.cs",
  "url": "https://github.com/NethermindEth/nethermind/src/Nethermind/Nethermind.Evm/Precompiles/PointEvaluationPrecompile.cs",
  "summary": "The `PointEvaluationPrecompile` class is a precompile implementation for the Ethereum Virtual Machine (EVM) that verifies a zero-knowledge proof of knowledge of a polynomial commitment. It is part of the Nethermind project, which is an Ethereum client implementation in .NET.\n\nThe `PointEvaluationPrecompile` class implements the `IPrecompile` interface, which defines the methods required for an EVM precompile. The `Address` property returns the precompile address, which is `0x14`. The `BaseGasCost` method returns the base gas cost for executing the precompile, which is `50000L`. The `DataGasCost` method returns the data gas cost for executing the precompile, which is `0`. The `Run` method executes the precompile with the given input data and returns the output data and a boolean indicating whether the execution was successful.\n\nThe `Run` method first checks whether the input data is valid by calling the `IsValid` method. The `IsValid` method checks whether the input data has the correct length and format, and whether the zero-knowledge proof is valid. If the input data is valid, the `Run` method returns a successful response that contains the number of field elements per blob and the modulus of the polynomial commitment. If the input data is invalid, the `Run` method returns an unsuccessful response.\n\nThe `PointEvaluationPrecompile` class uses several classes from the Nethermind project, including `Address`, `KzgPolynomialCommitments`, and `Metrics`. The `Address` class is used to create an Ethereum address from a number. The `KzgPolynomialCommitments` class is used to compute and verify polynomial commitments. The `Metrics` class is used to track the number of times the precompile is executed.\n\nThe `PointEvaluationPrecompile` class is used in the larger Nethermind project as an EVM precompile that can be called by smart contracts. Smart contracts can use the precompile to verify zero-knowledge proofs of knowledge of polynomial commitments, which can be used in various applications such as anonymous voting, private transactions, and secure multiparty computation. The precompile is designed to be efficient and secure, and is optimized for the .NET platform.",
  "questions": "1. What is the purpose of this code and what problem does it solve?\n    \n    This code defines a precompile for the Ethereum Virtual Machine (EVM) that performs point evaluation for a specific cryptographic scheme. It verifies input data and returns a response if the input is valid.\n\n2. What dependencies does this code have?\n    \n    This code depends on several other modules within the Nethermind project, including `Nethermind.Core`, `Nethermind.Core.Specs`, and `Nethermind.Crypto`. It also uses the `System` and `System.Linq` namespaces.\n\n3. What is the expected input format for this precompile and how is it validated?\n    \n    The expected input format is a 192-byte array containing a versioned hash, z and y values, a commitment, and a proof. The input is validated by checking its length, computing a hash of the commitment, verifying that the hash matches the versioned hash, and verifying the proof using the commitment, z, y, and proof values."
}